nonebot_plugin_BAdrawcard/__init__.py
nonebot_plugin_BAdrawcard/config.py
nonebot_plugin_BAdrawcard/Data/background.jpg
nonebot_plugin_BAdrawcard/Data/cd.json
nonebot_plugin_BAdrawcard/Data/ji.jpg
nonebot_plugin_BAdrawcard/Data/student_icons/.gitkeep
nonebot_plugin_BAdrawcard/Data/white.json
nonebot_plugin_BAdrawcard/db.py
nonebot_plugin_BAdrawcard/draw.py
nonebot_plugin_BAdrawcard/main.py
nonebot_plugin_BAdrawcard/manage.py
nonebot_plugin_BAdrawcard/models.py
nonebot_plugin_BAdrawcard/pull.py
nonebot_plugin_BAdrawcard/spider.py
nonebot_plugin_BAdrawcard/utils.py
nonebot_plugin_badrawcard-0.2.3.dist-info/LICENSE
nonebot_plugin_badrawcard-0.2.3.dist-info/METADATA
nonebot_plugin_badrawcard-0.2.3.dist-info/WHEEL
nonebot_plugin_badrawcard-0.2.3.dist-info/RECORD
