Metadata-Version: 2.1
Name: nonebot-plugin-badrawcard
Version: 0.2.3
Summary: 模拟BA抽卡
Author: LMZZ
Requires-Python: >=3.8,<4.0
Classifier: Programming Language :: Python :: 3
Classifier: Programming Language :: Python :: 3.8
Classifier: Programming Language :: Python :: 3.9
Classifier: Programming Language :: Python :: 3.10
Classifier: Programming Language :: Python :: 3.11
Requires-Dist: aiofiles (>=23.2.1,<24.0.0)
Requires-Dist: nonebot-plugin-apscheduler (>=0.3.0,<0.4.0)
Requires-Dist: nonebot-plugin-send-anything-anywhere (>=0.5.0,<0.6.0)
Requires-Dist: nonebot2[httpx] (>=2.1.3,<3.0.0)
Requires-Dist: pillow (>=10.0.1,<11.0.0)
Requires-Dist: pydantic[dotenv] (>=1.10.0,<2.0.0)
Requires-Dist: redis (>=5.0.0,<6.0.0)
